[
  {
    "date": "2021-02-01",
    "saleName": "ポイント２倍デー"
  },
  {
    "date": "2021-02-01",
    "saleName": "紙製品ポイント3倍デー"
  },
  {
    "date": "2021-02-02",
    "saleName": "ポイント２倍デー"
  },
  {
    "date": "2021-02-02",
    "saleName": "均一セール"
  },
  {
    "date": "2021-02-03",
    "saleName": "ポイント２倍デー"
  },
  {
    "date": "2021-02-03",
    "saleName": "たまごの日"
  },
  {
    "date": "2021-02-03",
    "saleName": "均一セール"
  },
  {
    "date": "2021-02-05",
    "saleName": "酒ポイント３倍デー"
  },
  {
    "date": "2021-02-07",
    "saleName": "たまごの日"
  },
  {
    "date": "2021-02-08",
    "saleName": "紙製品ポイント3倍デー"
  },
  {
    "date": "2021-02-09",
    "saleName": "均一セール"
  },
  {
    "date": "2021-02-10",
    "saleName": "たまごの日"
  },
  {
    "date": "2021-02-10",
    "saleName": "均一セール"
  },
  {
    "date": "2021-02-12",
    "saleName": "酒ポイント３倍デー"
  },
  {
    "date": "2021-02-14",
    "saleName": "ポイント3倍デー（フォルテ津田沼店を除く）"
  },
  {
    "date": "2021-02-15",
    "saleName": "紙製品ポイント3倍デー"
  },
  {
    "date": "2021-02-16",
    "saleName": "お米ポイント3倍デー（フォルテ津田沼店を除く）"
  },
  {
    "date": "2021-02-16",
    "saleName": "均一セール"
  },
  {
    "date": "2021-02-17",
    "saleName": "たまごの日"
  },
  {
    "date": "2021-02-17",
    "saleName": "均一セール"
  },
  {
    "date": "2021-02-19",
    "saleName": "酒ポイント３倍デー"
  },
  {
    "date": "2021-02-21",
    "saleName": "たまごの日"
  },
  {
    "date": "2021-02-22",
    "saleName": "紙製品ポイント3倍デー"
  },
  {
    "date": "2021-02-23",
    "saleName": "均一セール"
  },
  {
    "date": "2021-02-24",
    "saleName": "たまごの日"
  },
  {
    "date": "2021-02-24",
    "saleName": "均一セール"
  },
  {
    "date": "2021-02-26",
    "saleName": "酒ポイント３倍デー"
  }
]